neo4pydantic/__init__.py
neo4pydantic/exceptions.py
neo4pydantic/async_/__init__.py
neo4pydantic/async_/base.py
neo4pydantic/async_/client.py
neo4pydantic/async_/index_manager.py
neo4pydantic/core/__init__.py
neo4pydantic/core/base.py
neo4pydantic/core/custom_base_model.py
neo4pydantic/core/index_registry.py
neo4pydantic/examples/__init__.py
neo4pydantic/examples/async_examples.py
neo4pydantic/examples/sync_examples.py
neo4pydantic/sync/__init__.py
neo4pydantic/sync/base.py
neo4pydantic/sync/client.py
neo4pydantic/sync/index_manager.py
neo4pydantic/utils/__init__.py
neo4pydantic/utils/types.py
neo4pydantic-0.1.1.dist-info/licenses/LICENSE
neo4pydantic-0.1.1.dist-info/METADATA
neo4pydantic-0.1.1.dist-info/WHEEL
neo4pydantic-0.1.1.dist-info/top_level.txt
neo4pydantic-0.1.1.dist-info/RECORD
